moviesorter.sample.yml
moviesorter/__init__.py
moviesorter/cli.py
moviesorter/config.py
moviesorter/metadata.py
moviesorter/parser.py
moviesorter/sorter.py
moviesorter-0.0.11.dist-info/entry_points.txt
moviesorter-0.0.11.dist-info/LICENSE
moviesorter-0.0.11.dist-info/WHEEL
moviesorter-0.0.11.dist-info/METADATA
moviesorter-0.0.11.dist-info/RECORD
