Metadata-Version: 2.1
Name: moviesorter
Version: 0.0.11
Summary: 
License: GPL-3.0
Requires-Python: >=3.11,<4.0
Classifier: License :: OSI Approved :: GNU General Public License v3 (GPLv3)
Classifier: Programming Language :: Python :: 3
Classifier: Programming Language :: Python :: 3.11
Requires-Dist: PyYAML (>=6.0,<7.0)
Requires-Dist: aiohttp (>=3.8.3,<4.0.0)
Requires-Dist: async-cache (>=1.1.1,<2.0.0)
Requires-Dist: click (>=8.1.3,<9.0.0)
Requires-Dist: pydantic (>=1.10.4,<2.0.0)
Requires-Dist: rich (>=13.1.0,<14.0.0)
